{"title":"","uid":"f73a8e23e6f6f669cf99c7dba8fa0722","slug":"Java/Java版本新特性/Java9","date":"2022-06-27T12:43:32.656Z","updated":"2022-06-27T12:43:11.000Z","comments":true,"path":"api/articles/Java/Java版本新特性/Java9.json","keywords":null,"cover":null,"content":"","text":"","link":"","photos":[],"count_time":{"symbolsCount":0,"symbolsTime":"1 mins."},"categories":[],"tags":[],"toc":"","author":{"name":"Hyc","slug":"blog-author","avatar":"https://img-blog.csdnimg.cn/20210313122054101.png","link":"/","description":"努力成为六边形战士","socials":{"github":"","twitter":"","stackoverflow":"","wechat":"","qq":"","weibo":"","zhihu":"","csdn":"","juejin":"","customs":{}}},"mapped":true,"prev_post":{"title":"Git","uid":"221a7ad001c03569112f684b2dfdc120","slug":"工具/Git","date":"2022-06-27T12:43:32.687Z","updated":"2022-06-27T12:43:11.000Z","comments":true,"path":"api/articles/工具/Git.json","keywords":null,"cover":null,"text":"Git概述简介Git命令","link":"","photos":[],"count_time":{"symbolsCount":12,"symbolsTime":"1 mins."},"categories":[{"name":"工具","slug":"工具","count":2,"path":"api/categories/工具.json"}],"tags":[],"author":{"name":"Hyc","slug":"blog-author","avatar":"https://img-blog.csdnimg.cn/20210313122054101.png","link":"/","description":"努力成为六边形战士","socials":{"github":"","twitter":"","stackoverflow":"","wechat":"","qq":"","weibo":"","zhihu":"","csdn":"","juejin":"","customs":{}}},"feature":true},"next_post":{"title":"","uid":"f73a8e23e6f6f669cf99c7dba8fa0722","slug":"Java/Java版本新特性/Java8","date":"2022-06-27T12:43:32.654Z","updated":"2022-06-27T12:43:11.000Z","comments":true,"path":"api/articles/Java/Java版本新特性/Java8.json","keywords":null,"cover":null,"text":"","link":"","photos":[],"count_time":{"symbolsCount":0,"symbolsTime":"1 mins."},"categories":[],"tags":[],"author":{"name":"Hyc","slug":"blog-author","avatar":"https://img-blog.csdnimg.cn/20210313122054101.png","link":"/","description":"努力成为六边形战士","socials":{"github":"","twitter":"","stackoverflow":"","wechat":"","qq":"","weibo":"","zhihu":"","csdn":"","juejin":"","customs":{}}}}}